datahub_postgres_lineage/__init__.py
datahub_postgres_lineage/ingestion.py
datahub_postgres_lineage-0.1.3.dist-info/METADATA
datahub_postgres_lineage-0.1.3.dist-info/LICENSE
datahub_postgres_lineage-0.1.3.dist-info/WHEEL
datahub_postgres_lineage-0.1.3.dist-info/RECORD
